dcm/__init__.py
dcm/dcm_assessment.py
dcm/dcm_chart.py
dcm/dcm_cmd.py
dcm/dcm_core.py
dcm/dcm_web.py
dcm/dcm_webserver.py
dcm/radar_chart.py
dcm/svg.py
dcm/version.py
dcm/xapi.py
dcm/linkml/__init__.py
dcm/linkml/dcm.context.jsonld
dcm/linkml/dcm_model.py
dcm/linkml/dcm_schema.yaml
dcm/linkml/gen
dcm_examples/__init__.py
dcm_examples/arch_student_123.json
dcm_examples/architecture-KIT2021.yaml
dcm_examples/architecture.yaml
dcm_examples/greta.yaml
dcm_examples/greta_learner_xapi_example1.json
dcm_examples/greta_text.yaml
dcm_examples/isaqb_cpsa-f_2025_de.yaml
dcm_examples/isaqb_cpsa-f_2025_en.yaml
dcm_examples/isaqb_cpsa-f_de.yaml
dcm_examples/isaqb_cpsa-f_en.yaml
dcm_examples/portfolio_plus.y
dcm_examples/rwth_aachen_master_informatik.yaml
dynamic_competence_map-0.3.0.dist-info/METADATA
dynamic_competence_map-0.3.0.dist-info/WHEEL
dynamic_competence_map-0.3.0.dist-info/entry_points.txt
dynamic_competence_map-0.3.0.dist-info/licenses/LICENSE
dynamic_competence_map-0.3.0.dist-info/RECORD
