Metadata-Version: 2.4
Name: dynamic_competence_map
Version: 0.3.0
Summary: dcm: nicegui based visualization of dynamic competence map
Project-URL: Home, https://github.com/WolfgangFahl/dcm
Project-URL: Documentation, https://wiki.bitplan.com/index.php/dcm
Project-URL: Source, https://github.com/WolfgangFahl/dcm
Author-email: Wolfgang Fahl <wf@WolfgangFahl.com>
Maintainer-email: Wolfgang Fahl <wf@WolfgangFahl.com>
License: Apache-2.0
License-File: LICENSE
Keywords: competence,nicegui,skills
Classifier: Development Status :: 4 - Beta
Classifier: Environment :: Web Environment
Classifier: Intended Audience :: Developers
Classifier: Intended Audience :: Education
Classifier: Intended Audience :: Science/Research
Classifier: License :: OSI Approved :: Apache Software License
Classifier: Operating System :: OS Independent
Classifier: Programming Language :: Python :: 3 :: Only
Classifier: Programming Language :: Python :: 3.10
Classifier: Programming Language :: Python :: 3.11
Classifier: Programming Language :: Python :: 3.12
Classifier: Programming Language :: Python :: 3.13
Classifier: Topic :: Software Development :: User Interfaces
Requires-Python: >=3.10
Requires-Dist: colour>=0.1.5
Requires-Dist: dataclasses-json>=0.6.1
Requires-Dist: linkml
Requires-Dist: linkml-runtime
Requires-Dist: markdown2<2.4.11,>=2.4.7
Requires-Dist: ngwidgets>=0.27.1
Requires-Dist: pybasemkit>=0.0.3
Requires-Dist: python-slugify>=8.0.1
Requires-Dist: rdflib
Provides-Extra: test
Requires-Dist: green; extra == 'test'
